README.md
setup.py
py_cui/__init__.py
py_cui/colors.py
py_cui/debug.py
py_cui/errors.py
py_cui/grid.py
py_cui/keys.py
py_cui/popups.py
py_cui/renderer.py
py_cui/statusbar.py
py_cui/ui.py
py_cui/widget_set.py
py_cui/widgets.py
py_cui/controls/__init__.py
py_cui/controls/slider.py
py_cui/dialogs/__init__.py
py_cui/dialogs/filedialog.py
py_cui/dialogs/form.py
py_cui_fork.egg-info/PKG-INFO
py_cui_fork.egg-info/SOURCES.txt
py_cui_fork.egg-info/dependency_links.txt
py_cui_fork.egg-info/requires.txt
py_cui_fork.egg-info/top_level.txt